asyncakinator/__init__.py
asyncakinator/akinator.py
asyncakinator/exceptions.py
asyncakinator/models.py
asyncakinator/utils.py
asyncakinator-1.7.dist-info/LICENSE
asyncakinator-1.7.dist-info/METADATA
asyncakinator-1.7.dist-info/WHEEL
asyncakinator-1.7.dist-info/top_level.txt
asyncakinator-1.7.dist-info/RECORD
