Metadata-Version: 2.1
Name: asyncakinator
Version: 1.7
Summary: An async API wrapper for Akinator, written in Python.
Author-email: avizum <juliusrt@outlook.com>
License: MIT License
Project-URL: Home Page, https://github.com/avizum/asyncakinator
Project-URL: Documentation, https://asyncakinator.readthedocs.io/
Project-URL: Repository, https://github.com/avizum/asyncakinato
Classifier: Programming Language :: Python :: 3.9
Classifier: Programming Language :: Python :: 3.10
Classifier: Programming Language :: Python :: 3.11
Classifier: Development Status :: 5 - Production/Stable
Classifier: Intended Audience :: Developers
Classifier: Natural Language :: English
Classifier: License :: OSI Approved :: MIT License
Classifier: Operating System :: OS Independent
Classifier: Topic :: Software Development :: Libraries
Classifier: Topic :: Software Development :: Libraries :: Python Modules
Classifier: Topic :: Internet
Classifier: Topic :: Utilities
Requires-Python: >=3.9
License-File: LICENSE
Requires-Dist: aiohttp >=3.8.1
Provides-Extra: docs
Requires-Dist: sphinx ==6.1.1 ; extra == 'docs'
Requires-Dist: sphinxcontrib-trio ==1.1.2 ; extra == 'docs'
Requires-Dist: sphinx-copybutton ==0.5.1 ; extra == 'docs'
Requires-Dist: sphinx-inline-tabs ==2022.1.2b11 ; extra == 'docs'
Requires-Dist: furo ==2022.12.7 ; extra == 'docs'
Requires-Dist: setuptools ==65.6.3 ; extra == 'docs'
